{
  "id": "c52ef747-924d-40b9-a62a-75b23189b381",
  "category": "蔬菜",
  "name": "凉拌油麦菜",
  "description": "",
  "source_path": "dishes/vegetable_dish/凉拌油麦菜.md",
  "image_id": null,
  "image": "",
  "video_link": [],
  "difficulty": 1,
  "servings": 2,
  "kitchen_ware": [],
  "ingredients": [
    {
      "name": "油麦菜",
      "amount": 1,
      "unit": "颗",
      "remake": "约200g"
    },
    {
      "name": "醋",
      "amount": 15,
      "unit": "毫升"
    },
    {
      "name": "酱油",
      "amount": 5,
      "unit": "毫升"
    },
    {
      "name": "芝麻酱",
      "amount": 10,
      "unit": "毫升"
    },
    {
      "name": "香油",
      "amount": 5,
      "unit": "毫升"
    },
    {
      "name": "糖",
      "amount": 5,
      "unit": "克"
    },
    {
      "name": "蚝油",
      "amount": 10,
      "unit": "毫升"
    },
    {
      "name": "蒜",
      "amount": 2,
      "unit": "头"
    }
  ],
  "steps": [
    {
      "description": "蒜拍碎切末",
      "time_unit": "分钟",
      "time": [
        1,
        2
      ],
      "time_type": "take",
      "work_stage": "deal"
    },
    {
      "description": "醋，酱油，芝麻酱，香油，糖，蚝油，蒜末放到碗里搅拌均匀",
      "time_unit": "分钟",
      "time": [
        1,
        2
      ],
      "time_type": "take",
      "work_stage": "deal"
    },
    {
      "description": "油麦菜切段，每段不超过4cm",
      "time_unit": "分钟",
      "time": [
        2,
        3
      ],
      "time_type": "take",
      "work_stage": "deal"
    },
    {
      "description": "油麦菜放到一个大点的盆里，倒入上述碗中酱料，充分搅拌均匀",
      "time_unit": "分钟",
      "time": [
        1,
        2
      ],
      "time_type": "take",
      "work_stage": "cook"
    }
  ],
  "take_time": [
    5,
    9
  ],
  "wait_time": [
    0,
    0
  ],
  "total_time": [
    5,
    9
  ],
  "additional_notes": [
    {
      "type": "list_item",
      "content": "芝麻酱可以用花生酱代替"
    },
    {
      "type": "list_item",
      "content": "芝麻酱一定要和油麦菜混合均匀才更好吃."
    }
  ]
}